quasigraph/__init__.py
quasigraph/ptable.py
quasigraph/quasigraph.py
quasigraph-25.3.2.dist-info/METADATA
quasigraph-25.3.2.dist-info/WHEEL
quasigraph-25.3.2.dist-info/licenses/LICENSE.txt
quasigraph-25.3.2.dist-info/RECORD
