Metadata-Version: 2.4
Name: quasigraph
Version: 25.3.2
Summary: quasigraph: Chemical and Geometric Descriptor Toolkit for Machine Learning Models.
Project-URL: Homepage, https://github.com/leseixas/quasigraph
Author-email: Leandro Seixas <leandro.fisica@gmail.com>
License-File: LICENSE.txt
Classifier: License :: OSI Approved :: MIT License
Classifier: Operating System :: OS Independent
Classifier: Programming Language :: Python :: 3
Classifier: Topic :: Scientific/Engineering :: Chemistry
Classifier: Topic :: Scientific/Engineering :: Physics
Requires-Python: >=3.8
Requires-Dist: acat
Requires-Dist: ase
Requires-Dist: mendeleev
Requires-Dist: numpy
Requires-Dist: pandas
